Workbook

Sheet Resumen
A1: Indicador | B1: Valor
A2: Temas por estado
A3: Pendiente | B3: =COUNTIFS('Seguimiento temas'!B:B,"TEMA",'Seguimiento temas'!K:K,"01 - Pendiente") -> 2
A4: En curso | B4: =COUNTIFS('Seguimiento temas'!B:B,"TEMA",'Seguimiento temas'!K:K,"02 - En curso") -> 1
A5: En revision | B5: =COUNTIFS('Seguimiento temas'!B:B,"TEMA",'Seguimiento temas'!K:K,"03 - En revisión") -> 1
A6: Cerrado | B6: =COUNTIFS('Seguimiento temas'!B:B,"TEMA",'Seguimiento temas'!K:K,"04 - Cerrado") -> 1
A7: Bloqueado | B7: =COUNTIFS('Seguimiento temas'!B:B,"TEMA",'Seguimiento temas'!K:K,"05 - Bloqueado") -> 1
A8: Temas vencidos | B8: =COUNTIFS('Seguimiento temas'!B:B,"TEMA",'Seguimiento temas'!S:S,"Si") -> 5
A9: Hitos vencidos | B9: =COUNTIFS('Seguimiento temas'!B:B,"HITO",'Seguimiento temas'!S:S,"Si") -> 0
A10: Temas con expediente | B10: =COUNTIFS('Seguimiento temas'!B:B,"TEMA",'Seguimiento temas'!L:L,"<>") -> 1
A11: Total de temas en este reporte | B11: =COUNTIF('Seguimiento temas'!B:B,"TEMA") -> 6

Sheet Seguimiento temas
A2: Fecha | B2: Nivel | C2: ID Tema | D2: Etiquetas | E2: Solicitante | F2: Importancia | G2: Provincia | H2: Municipio | I2: Hito / Tema | J2: Responsable | K2: Estado | L2: Expediente | M2: Dependencia | N2: Fecha de inicio | O2: Fecha de finalización | P2: Dias restantes para su finalizacion | Q2: Última actualización | R2: Fecha última act | S2: Vencido | T2: Privado
A3: 46146 | B3: TEMA | C3: T-001 | E3: Valeria Ricco | F3: Media | I3: Declaración Jurada Anual de Patrimonio (periodo 2025) | J3: Jorge Ríos | K3: 01 - Pendiente | N3: 46146 | O3: 46234 | P3: =IF(K3="04 - Cerrado","-",O3-TODAY()) -> -1 | Q3: VTO 31 de julio de 2026 Jorge avisado el 26/5 | S3: =IF(AND(K3<>"04 - Cerrado",O3<TODAY()),"Si","No") -> Si | T3: No
A4: 46146 | B4: HITO | C4: T-001 | I4: Recibir pedido de la Oficina Anticorrupción: NO-2026-44395169-APN-SSGAI#MEC y NO-2026-44394584-APN-SSGAI#MEC | J4: Jorge Ríos | K4: 04 - Cerrado | S4: - | T4: No
A5: 46146 | B5: HITO | C5: T-001 | I5: Completar declaración con modelo periodo 2024 | J5: Jorge Ríos | K5: 01 - Pendiente | S5: - | T5: No
A6: 46146 | B6: HITO | C6: T-001 | I6: Presentar declaración jurada | J6: Jorge Ríos | K6: 01 - Pendiente | S6: - | T6: No
A7: 46161 | B7: TEMA | C7: T-002 | D7: Obra, NRU | E7: Natalia Hilu, Pablo Morillo | F7: Baja | G7: Tucuman | I7: NRU 1763 - Barrio Avenida de las Americas - Municipalidad de Concepcion | J7: Luis Mesones, Alejandro Balbo | K7: 02 - En curso | L7: EX-2022-94776460-APN-CEFISU#MDS | N7: 46161 | O7: 46213 | P7: =IF(K7="04 - Cerrado","-",O7-TODAY()) -> -22 | Q7: Pendiente de auditoria externa | S7: =IF(AND(K7<>"04 - Cerrado",O7<TODAY()),"Si","No") -> Si | T7: No
A8: 46161 | B8: HITO | C8: T-002 | I8: Validacion del certificado de avance de obra N02 (60%) por auditor externo | J8: Alejandro Balbo | K8: 04 - Cerrado | S8: - | T8: No
B9: HITO | C9: T-002 | I9: Elevacion de expediente para aprobacion del 3 desembolso | J9: Alejandro Balbo | K9: 01 - Pendiente | M9: Validacion del certificado de avance de obra N02 (60%) por auditor externo — FC | S9: - | T9: No
A10: 46162 | B10: TEMA | C10: T-003 | D10: Licitacion, Concesion | E10: Ignacio Lupi | F10: Alta | G10: Ciudad Autonoma de Buenos Aires | I10: Concesion Palais de Glace | J10: Luisina Roa, Karina Leone | K10: 05 - Bloqueado | N10: 46162 | O10: 46218 | P10: =IF(K10="04 - Cerrado","-",O10-TODAY()) -> -17 | Q10: A la espera de pliegos | S10: =IF(AND(K10<>"04 - Cerrado",O10<TODAY()),"Si","No") -> Si | T10: Si
A11: 46162 | B11: HITO | C11: T-003 | I11: Confeccion de pliegos | J11: Luisina Roa | K11: 02 - En curso | S11: - | T11: Si
B12: HITO | C12: T-003 | I12: Llamado a licitacion | J12: Karina Leone | K12: 05 - Bloqueado | M12: Confeccion de pliegos — FC | S12: - | T12: Si
A13: 46181 | B13: TEMA | C13: T-004 | D13: Reunion, Externo | E13: Externo | F13: Alta | I13: Solicitud de reunion Gustavo Coria (Secretario de Interior) | J13: Jorge Rios, Privada | K13: 04 - Cerrado | N13: 46181 | O13: 46185 | P13: =IF(K13="04 - Cerrado","-",O13-TODAY()) -> - | Q13: Reunion realizada el 12/6 | S13: =IF(AND(K13<>"04 - Cerrado",O13<TODAY()),"Si","No") -> No | T13: No
A14: 46177 | B14: TEMA | C14: T-005 | D14: Convenio | E14: Nicolas Mantegazza | F14: Media | G14: Buenos Aires | H14: San Vicente | I14: Estado de situacion de los temas Intendente San Vicente | J14: Jorge Rios, Marielda Romero | K14: 03 - En revisión | N14: 46177 | O14: 46193 | P14: =IF(K14="04 - Cerrado","-",O14-TODAY()) -> -42 | Q14: En revision por el area tecnica | S14: =IF(AND(K14<>"04 - Cerrado",O14<TODAY()),"Si","No") -> Si | T14: No
A15: 46177 | B15: HITO | C15: T-005 | I15: Enviar estado de situacion de procrear | J15: Jorge Rios | K15: 03 - En revisión | S15: - | T15: No
A16: 46188 | B16: TEMA | C16: T-006 | D16: Auditoria | E16: Direccion de Auditoria | F16: Alta | I16: Auditoria de rendiciones de fondos 2025 | J16: R. Castro | K16: 01 - Pendiente | N16: 46188 | O16: 46208 | P16: =IF(K16="04 - Cerrado","-",O16-TODAY()) -> -27 | Q16: Falta designar equipo auditor | S16: =IF(AND(K16<>"04 - Cerrado",O16<TODAY()),"Si","No") -> Si | T16: Si
A17: 46188 | B17: HITO | C17: T-006 | I17: Designar equipo auditor | J17: R. Castro | K17: 01 - Pendiente | S17: - | T17: Si
B18: HITO | C18: T-006 | I18: Relevar rendiciones pendientes | J18: R. Castro | K18: 01 - Pendiente | M18: Designar equipo auditor — CC | S18: - | T18: Si

Sheet Leyenda
A1: Estados
A2: 01 - Pendiente | B2: El tema o hito está anotado pero todavía no arrancó ningún trabajo sobre él. No hay ningún impedimento externo: simplemente no se empezó, sea porque no llegó su turno de prioridad o porque su fecha de inicio prevista todavía no llegó. Ejemplo: un hito recién creado que espera a que se libere el responsable, o un trámite que se sabe que hay que iniciar pero que aún no se gestionó.
A3: 02 - En curso | B3: Hay trabajo activo sucediendo ahora mismo: alguien lo está redactando, coordinando, auditando o ejecutando en este momento. Ejemplo: el responsable está armando la documentación, coordinando una reunión, o la obra está en ejecución.
A4: 03 - En revisión | B4: El trabajo de fondo ya está terminado; lo único que falta es que un tercero lo revise, valide, apruebe o firme antes de poder cerrarlo. No depende de generar más contenido, sino de que alguien más lo mire. Ejemplo: un informe redactado que espera la firma de un Secretario, o una rendición ya armada que está en poder de auditoría externa.
A5: 04 - Cerrado | B5: Está completado y no requiere ninguna acción adicional de nadie. Ejemplo: expediente firmado y archivado, hito cumplido y verificado, reunión realizada y sin pendientes posteriores.
A6: 05 - Bloqueado | B6: No puede avanzar porque depende de un tercero o de algo externo que todavía no está resuelto. La diferencia con "Pendiente" es que acá ya se intentó avanzar pero hay un impedimento concreto identificado. Ejemplo: el hito de elevación del expediente en T-002 es "Bloqueado" y no "Pendiente" porque está esperando que se apruebe la rendición contable —no es que no arrancó, es que está frenado por algo fuera del equipo.
A8: Importancia
A9: Alta | B9: Tiene alta exposición institucional: involucra a autoridades (Ministro, Secretarios, intendentes), compromisos públicos ya asumidos, o su demora genera un riesgo concreto -legal, presupuestario o de imagen-. Se prioriza por encima del resto de la agenda. Ejemplo: pedido de reunión de un intendente, expediente con vencimiento normativo, compromiso ya comunicado públicamente.
A10: Media | B10: Afecta la gestión habitual del área pero no compromete al Ministerio frente a terceros de forma crítica si se demora unos días. Tiene plazos, aunque con margen razonable de reprogramación. Ejemplo: seguimiento de una obra en curso sin alertas activas, actualización de un convenio sin fecha límite inminente.
A11: Baja | B11: Bajo impacto o urgencia: puede posponerse sin consecuencias relevantes ni para el área ni para terceros. Se resuelve cuando hay disponibilidad, sin correr al resto de la agenda. Ejemplo: trámites administrativos de rutina, actualizaciones internas sin fecha de vencimiento definida.
A12: Nota | B12: "Importancia" clasifica la prioridad de gestión del tema, no si está vencido. Un tema de Importancia Baja puede estar vencido igual (ver columna Vencido en "Seguimiento temas"), sin que eso lo vuelva Alta automáticamente.
